simplepipe.py
simplepipe-0.0.5.3.dist-info/DESCRIPTION.rst
simplepipe-0.0.5.3.dist-info/METADATA
simplepipe-0.0.5.3.dist-info/RECORD
simplepipe-0.0.5.3.dist-info/WHEEL
simplepipe-0.0.5.3.dist-info/metadata.json
simplepipe-0.0.5.3.dist-info/top_level.txt
