Metadata-Version: 2.0
Name: simplepipe
Version: 0.0.5.3
Summary: A simple functional pipelining library for Python.
Home-page: https://github.com/thomasantony/simplepipe
Author: Thomas Antony
Author-email: tantony.purdue@gmail.com
License: MIT
Keywords: pipeline,functional,functional programming
Platform: UNKNOWN
Classifier: Development Status :: 3 - Alpha
Classifier: Topic :: Software Development :: Libraries
Classifier: Intended Audience :: Developers
Classifier: Programming Language :: Python
Classifier: Programming Language :: Python :: 3
Classifier: Programming Language :: Python :: 3.3
Classifier: Programming Language :: Python :: 3.4
Classifier: Programming Language :: Python :: 3.5
Classifier: License :: OSI Approved :: MIT License
